NeuroEvolution/RL.py
NeuroEvolution/__init__.py
NeuroEvolution/layer_classes.py
NeuroEvolution/optimizer.py
neuroevolution-1.0.0.dist-info/METADATA
neuroevolution-1.0.0.dist-info/WHEEL
neuroevolution-1.0.0.dist-info/top_level.txt
neuroevolution-1.0.0.dist-info/RECORD
