Metadata-Version: 2.4
Name: NeuroEvolution
Version: 1.0.0
Summary: Neuro-evolution and model optimization toolkit
Author: Romain Amigon
License: MIT
Requires-Python: >=3.0
Requires-Dist: numpy
Requires-Dist: torch
Requires-Dist: scikit-learn
Requires-Dist: mealpy
Requires-Dist: torchvision
